{
  "hash": "807ecc50",
  "browserHash": "0c94226f",
  "optimized": {
    "vue": {
      "src": "../../../../../../node_modules/vue/dist/vue.runtime.esm-bundler.js",
      "file": "vue.js",
      "fileHash": "e37cd59b",
      "needsInterop": false
    },
    "vitepress > @vue/devtools-api": {
      "src": "../../../../../../node_modules/@vue/devtools-api/lib/esm/index.js",
      "file": "vitepress___@vue_devtools-api.js",
      "fileHash": "4fcee50c",
      "needsInterop": false
    }
  },
  "chunks": {}
}